dasflow/__init__.py
dasflow/hough_detect.py
dasflow/model.py
dasflow/model_detect.py
dasflow/model_train.py
dasflow/preprocess.py
dasflow/tmf.py
dasflow-0.0.7.dist-info/METADATA
dasflow-0.0.7.dist-info/WHEEL
dasflow-0.0.7.dist-info/top_level.txt
dasflow-0.0.7.dist-info/RECORD
