Metadata-Version: 2.1
Name: dasflow
Version: 0.0.7
Summary: DAS event detection flow based on deep learning
Home-page: 
Author: Hao Lv
Author-email: lh21@apm.ac.cn
License: MIT
Classifier: Programming Language :: Python :: 3
Classifier: License :: OSI Approved :: MIT License
Classifier: Operating System :: OS Independent
Requires-Python: >=3.9
